cltl/dialogue_act_classification/__init__.py
cltl/dialogue_act_classification/add_dialogue_acts_to_emissor.py
cltl/dialogue_act_classification/api.py
cltl/dialogue_act_classification/midas_classifier.py
cltl/dialogue_act_classification/silicone_classifier.py
cltl.dialogueclassification-0.2.dev1.data/data/VERSION/VERSION
cltl_service/dialogue_act_classification/__init__.py
cltl_service/dialogue_act_classification/schema.py
cltl_service/dialogue_act_classification/service.py
cltl.dialogueclassification-0.2.dev1.dist-info/LICENSE
cltl.dialogueclassification-0.2.dev1.dist-info/METADATA
cltl.dialogueclassification-0.2.dev1.dist-info/WHEEL
cltl.dialogueclassification-0.2.dev1.dist-info/top_level.txt
cltl.dialogueclassification-0.2.dev1.dist-info/RECORD
