Metadata-Version: 2.1
Name: cltl.dialogueclassification
Version: 0.2.dev1
Summary: Template component for Leolani
Home-page: https://github.com/leolani/cltl-dialogueclassification
Author: CLTL
Author-email: t.baier@vu.nl
License: MIT License
Requires-Python: >=3.8
License-File: LICENSE
Provides-Extra: impl
Requires-Dist: transformers ; extra == 'impl'
Requires-Dist: torch ; extra == 'impl'
Requires-Dist: numpy ; extra == 'impl'
Provides-Extra: service
Requires-Dist: cltl.combot ; extra == 'service'
Requires-Dist: emissor ; extra == 'service'
